{
  "fio version" : "fio-2.1.11",
  "jobs" : [
    {
      "jobname" : "varwrite",
      "groupid" : 0,
      "error" : 0,
      "read" : {
        "io_bytes" : 72640,
        "bw" : 4713,
        "iops" : 147,
        "runtime" : 15410,
        "slat" : {
          "min" : 0,
          "max" : 0,
          "mean" : 0.00,
          "stddev" : 0.00
        },
        "clat" : {
          "min" : 112,
          "max" : 266854,
          "mean" : 6187.03,
          "stddev" : 7759.53,
          "percentile" : {
            "1.000000" : 139,
            "5.000000" : 165,
            "10.000000" : 207,
            "20.000000" : 466,
            "30.000000" : 740,
            "40.000000" : 3888,
            "50.000000" : 5984,
            "60.000000" : 7648,
            "70.000000" : 8512,
            "80.000000" : 8768,
            "90.000000" : 13888,
            "95.000000" : 17024,
            "99.000000" : 23424,
            "99.500000" : 25216,
            "99.900000" : 27008,
            "99.950000" : 32640,
            "99.990000" : 268288,
            "0.00" : 0,
            "0.00" : 0,
            "0.00" : 0
          }
        },
        "lat" : {
          "min" : 112,
          "max" : 266855,
          "mean" : 6187.72,
          "stddev" : 7759.54
        },
        "bw_min" : 2303,
        "bw_max" : 6834,
        "bw_agg" : 100.00,
        "bw_mean" : 4736.27,
        "bw_dev" : 1066.59
      },
      "write" : {
        "io_bytes" : 46368,
        "bw" : 3008,
        "iops" : 94,
        "runtime" : 15410,
        "slat" : {
          "min" : 0,
          "max" : 0,
          "mean" : 0.00,
          "stddev" : 0.00
        },
        "clat" : {
          "min" : 189,
          "max" : 240387,
          "mean" : 919.00,
          "stddev" : 8849.20,
          "percentile" : {
            "1.000000" : 199,
            "5.000000" : 213,
            "10.000000" : 235,
            "20.000000" : 294,
            "30.000000" : 314,
            "40.000000" : 350,
            "50.000000" : 374,
            "60.000000" : 426,
            "70.000000" : 684,
            "80.000000" : 876,
            "90.000000" : 1048,
            "95.000000" : 1160,
            "99.000000" : 1768,
            "99.500000" : 1944,
            "99.900000" : 232448,
            "99.950000" : 240640,
            "99.990000" : 240640,
            "0.00" : 0,
            "0.00" : 0,
            "0.00" : 0
          }
        },
        "lat" : {
          "min" : 191,
          "max" : 240389,
          "mean" : 921.65,
          "stddev" : 8849.19
        },
        "bw_min" : 1307,
        "bw_max" : 4790,
        "bw_agg" : 100.00,
        "bw_mean" : 3020.23,
        "bw_dev" : 747.34
      },
      "trim" : {
        "io_bytes" : 0,
        "bw" : 0,
        "iops" : 0,
        "runtime" : 0,
        "slat" : {
          "min" : 0,
          "max" : 0,
          "mean" : 0.00,
          "stddev" : 0.00
        },
        "clat" : {
          "min" : 0,
          "max" : 0,
          "mean" : 0.00,
          "stddev" : 0.00,
          "percentile" : {
            "1.000000" : 0,
            "5.000000" : 0,
            "10.000000" : 0,
            "20.000000" : 0,
            "30.000000" : 0,
            "40.000000" : 0,
            "50.000000" : 0,
            "60.000000" : 0,
            "70.000000" : 0,
            "80.000000" : 0,
            "90.000000" : 0,
            "95.000000" : 0,
            "99.000000" : 0,
            "99.500000" : 0,
            "99.900000" : 0,
            "99.950000" : 0,
            "99.990000" : 0,
            "0.00" : 0,
            "0.00" : 0,
            "0.00" : 0
          }
        },
        "lat" : {
          "min" : 0,
          "max" : 0,
          "mean" : 0.00,
          "stddev" : 0.00
        },
        "bw_min" : 0,
        "bw_max" : 0,
        "bw_agg" : 0.00,
        "bw_mean" : 0.00,
        "bw_dev" : 0.00
      },
      "usr_cpu" : 0.31,
      "sys_cpu" : 1.17,
      "ctx" : 3726,
      "majf" : 0,
      "minf" : 7,
      "iodepth_level" : {
        "1" : 100.00,
        "2" : 0.00,
        "4" : 0.00,
        "8" : 0.00,
        "16" : 0.00,
        "32" : 0.00,
        ">=64" : 0.00
      },
      "latency_us" : {
        "2" : 0.00,
        "4" : 0.00,
        "10" : 0.00,
        "20" : 0.00,
        "50" : 0.00,
        "100" : 0.00,
        "250" : 12.77,
        "500" : 26.19,
        "750" : 7.48,
        "1000" : 6.24
      },
      "latency_ms" : {
        "2" : 5.81,
        "4" : 5.00,
        "10" : 27.56,
        "20" : 7.45,
        "50" : 1.43,
        "100" : 0.00,
        "250" : 0.05,
        "500" : 0.03,
        "750" : 0.00,
        "1000" : 0.00,
        "2000" : 0.00,
        ">=2000" : 0.00
      },
      "latency_depth" : 1,
      "latency_target" : 0,
      "latency_percentile" : 100.00,
      "latency_window" : 0
    }
  ],
  "disk_util" : [
    {
      "name" : "sda",
      "read_ios" : 2269,
      "write_ios" : 1458,
      "read_merges" : 0,
      "write_merges" : 7,
      "read_ticks" : 13888,
      "write_ticks" : 2124,
      "in_queue" : 16128,
      "util" : 97.53
    }
  ]
}
