{
  "fio version" : "fio-2.1.11",
  "jobs" : [
    {
      "jobname" : "varwrite",
      "groupid" : 0,
      "error" : 0,
      "read" : {
        "io_bytes" : 126272,
        "bw" : 7864,
        "iops" : 122,
        "runtime" : 16056,
        "slat" : {
          "min" : 0,
          "max" : 0,
          "mean" : 0.00,
          "stddev" : 0.00
        },
        "clat" : {
          "min" : 205,
          "max" : 488723,
          "mean" : 7628.53,
          "stddev" : 16081.59,
          "percentile" : {
            "1.000000" : 274,
            "5.000000" : 354,
            "10.000000" : 394,
            "20.000000" : 580,
            "30.000000" : 3088,
            "40.000000" : 4576,
            "50.000000" : 6112,
            "60.000000" : 7456,
            "70.000000" : 8896,
            "80.000000" : 9920,
            "90.000000" : 15424,
            "95.000000" : 20864,
            "99.000000" : 32128,
            "99.500000" : 44800,
            "99.900000" : 411648,
            "99.950000" : 489472,
            "99.990000" : 489472,
            "0.00" : 0,
            "0.00" : 0,
            "0.00" : 0
          }
        },
        "lat" : {
          "min" : 206,
          "max" : 488724,
          "mean" : 7629.22,
          "stddev" : 16081.58
        },
        "bw_min" : 2154,
        "bw_max" : 15201,
        "bw_agg" : 100.00,
        "bw_mean" : 8065.23,
        "bw_dev" : 2498.88
      },
      "write" : {
        "io_bytes" : 78528,
        "bw" : 4890,
        "iops" : 76,
        "runtime" : 16056,
        "slat" : {
          "min" : 0,
          "max" : 0,
          "mean" : 0.00,
          "stddev" : 0.00
        },
        "clat" : {
          "min" : 259,
          "max" : 361559,
          "mean" : 789.13,
          "stddev" : 10312.14,
          "percentile" : {
            "1.000000" : 302,
            "5.000000" : 322,
            "10.000000" : 370,
            "20.000000" : 386,
            "30.000000" : 402,
            "40.000000" : 422,
            "50.000000" : 434,
            "60.000000" : 446,
            "70.000000" : 462,
            "80.000000" : 486,
            "90.000000" : 764,
            "95.000000" : 924,
            "99.000000" : 1640,
            "99.500000" : 1928,
            "99.900000" : 6112,
            "99.950000" : 362496,
            "99.990000" : 362496,
            "0.00" : 0,
            "0.00" : 0,
            "0.00" : 0
          }
        },
        "lat" : {
          "min" : 262,
          "max" : 361561,
          "mean" : 793.04,
          "stddev" : 10312.09
        },
        "bw_min" : 1992,
        "bw_max" : 9325,
        "bw_agg" : 100.00,
        "bw_mean" : 5008.17,
        "bw_dev" : 1623.20
      },
      "trim" : {
        "io_bytes" : 0,
        "bw" : 0,
        "iops" : 0,
        "runtime" : 0,
        "slat" : {
          "min" : 0,
          "max" : 0,
          "mean" : 0.00,
          "stddev" : 0.00
        },
        "clat" : {
          "min" : 0,
          "max" : 0,
          "mean" : 0.00,
          "stddev" : 0.00,
          "percentile" : {
            "1.000000" : 0,
            "5.000000" : 0,
            "10.000000" : 0,
            "20.000000" : 0,
            "30.000000" : 0,
            "40.000000" : 0,
            "50.000000" : 0,
            "60.000000" : 0,
            "70.000000" : 0,
            "80.000000" : 0,
            "90.000000" : 0,
            "95.000000" : 0,
            "99.000000" : 0,
            "99.500000" : 0,
            "99.900000" : 0,
            "99.950000" : 0,
            "99.990000" : 0,
            "0.00" : 0,
            "0.00" : 0,
            "0.00" : 0
          }
        },
        "lat" : {
          "min" : 0,
          "max" : 0,
          "mean" : 0.00,
          "stddev" : 0.00
        },
        "bw_min" : 0,
        "bw_max" : 0,
        "bw_agg" : 0.00,
        "bw_mean" : 0.00,
        "bw_dev" : 0.00
      },
      "usr_cpu" : 0.27,
      "sys_cpu" : 1.12,
      "ctx" : 3205,
      "majf" : 0,
      "minf" : 7,
      "iodepth_level" : {
        "1" : 100.00,
        "2" : 0.00,
        "4" : 0.00,
        "8" : 0.00,
        "16" : 0.00,
        "32" : 0.00,
        ">=64" : 0.00
      },
      "latency_us" : {
        "2" : 0.00,
        "4" : 0.00,
        "10" : 0.00,
        "20" : 0.00,
        "50" : 0.00,
        "100" : 0.00,
        "250" : 0.16,
        "500" : 42.81,
        "750" : 4.50,
        "1000" : 3.56
      },
      "latency_ms" : {
        "2" : 2.06,
        "4" : 7.62,
        "10" : 27.00,
        "20" : 8.88,
        "50" : 3.19,
        "100" : 0.09,
        "250" : 0.03,
        "500" : 0.09,
        "750" : 0.00,
        "1000" : 0.00,
        "2000" : 0.00,
        ">=2000" : 0.00
      },
      "latency_depth" : 1,
      "latency_target" : 0,
      "latency_percentile" : 100.00,
      "latency_window" : 0
    }
  ],
  "disk_util" : [
    {
      "name" : "sda",
      "read_ios" : 1934,
      "write_ios" : 1211,
      "read_merges" : 0,
      "write_merges" : 7,
      "read_ticks" : 14720,
      "write_ticks" : 2792,
      "in_queue" : 17508,
      "util" : 97.48
    }
  ]
}
