{
  "fio version" : "fio-2.1.11",
  "jobs" : [
    {
      "jobname" : "varwrite",
      "groupid" : 0,
      "error" : 0,
      "read" : {
        "io_bytes" : 163840,
        "bw" : 12131,
        "iops" : 47,
        "runtime" : 13505,
        "slat" : {
          "min" : 0,
          "max" : 0,
          "mean" : 0.00,
          "stddev" : 0.00
        },
        "clat" : {
          "min" : 602,
          "max" : 423069,
          "mean" : 20813.38,
          "stddev" : 27378.19,
          "percentile" : {
            "1.000000" : 668,
            "5.000000" : 708,
            "10.000000" : 740,
            "20.000000" : 4128,
            "30.000000" : 8512,
            "40.000000" : 10176,
            "50.000000" : 11200,
            "60.000000" : 21632,
            "70.000000" : 25728,
            "80.000000" : 33536,
            "90.000000" : 46336,
            "95.000000" : 53504,
            "99.000000" : 78336,
            "99.500000" : 96768,
            "99.900000" : 423936,
            "99.950000" : 423936,
            "99.990000" : 423936,
            "0.00" : 0,
            "0.00" : 0,
            "0.00" : 0
          }
        },
        "lat" : {
          "min" : 603,
          "max" : 423070,
          "mean" : 20814.09,
          "stddev" : 27378.20
        },
        "bw_min" : 932,
        "bw_max" : 19430,
        "bw_agg" : 99.76,
        "bw_mean" : 12101.56,
        "bw_dev" : 4041.93
      },
      "write" : {
        "io_bytes" : 40960,
        "bw" : 3032,
        "iops" : 11,
        "runtime" : 13505,
        "slat" : {
          "min" : 0,
          "max" : 0,
          "mean" : 0.00,
          "stddev" : 0.00
        },
        "clat" : {
          "min" : 769,
          "max" : 29684,
          "mean" : 1095.84,
          "stddev" : 2276.72,
          "percentile" : {
            "1.000000" : 788,
            "5.000000" : 812,
            "10.000000" : 820,
            "20.000000" : 844,
            "30.000000" : 852,
            "40.000000" : 868,
            "50.000000" : 876,
            "60.000000" : 900,
            "70.000000" : 932,
            "80.000000" : 996,
            "90.000000" : 1080,
            "95.000000" : 1160,
            "99.000000" : 1320,
            "99.500000" : 29568,
            "99.900000" : 29568,
            "99.950000" : 29568,
            "99.990000" : 29568,
            "0.00" : 0,
            "0.00" : 0,
            "0.00" : 0
          }
        },
        "lat" : {
          "min" : 779,
          "max" : 29700,
          "mean" : 1109.47,
          "stddev" : 2276.97
        },
        "bw_min" : 466,
        "bw_max" : 6603,
        "bw_agg" : 96.17,
        "bw_mean" : 2915.80,
        "bw_dev" : 1764.75
      },
      "trim" : {
        "io_bytes" : 0,
        "bw" : 0,
        "iops" : 0,
        "runtime" : 0,
        "slat" : {
          "min" : 0,
          "max" : 0,
          "mean" : 0.00,
          "stddev" : 0.00
        },
        "clat" : {
          "min" : 0,
          "max" : 0,
          "mean" : 0.00,
          "stddev" : 0.00,
          "percentile" : {
            "1.000000" : 0,
            "5.000000" : 0,
            "10.000000" : 0,
            "20.000000" : 0,
            "30.000000" : 0,
            "40.000000" : 0,
            "50.000000" : 0,
            "60.000000" : 0,
            "70.000000" : 0,
            "80.000000" : 0,
            "90.000000" : 0,
            "95.000000" : 0,
            "99.000000" : 0,
            "99.500000" : 0,
            "99.900000" : 0,
            "99.950000" : 0,
            "99.990000" : 0,
            "0.00" : 0,
            "0.00" : 0,
            "0.00" : 0
          }
        },
        "lat" : {
          "min" : 0,
          "max" : 0,
          "mean" : 0.00,
          "stddev" : 0.00
        },
        "bw_min" : 0,
        "bw_max" : 0,
        "bw_agg" : 0.00,
        "bw_mean" : 0.00,
        "bw_dev" : 0.00
      },
      "usr_cpu" : 0.15,
      "sys_cpu" : 0.41,
      "ctx" : 803,
      "majf" : 0,
      "minf" : 7,
      "iodepth_level" : {
        "1" : 100.00,
        "2" : 0.00,
        "4" : 0.00,
        "8" : 0.00,
        "16" : 0.00,
        "32" : 0.00,
        ">=64" : 0.00
      },
      "latency_us" : {
        "2" : 0.00,
        "4" : 0.00,
        "10" : 0.00,
        "20" : 0.00,
        "50" : 0.00,
        "100" : 0.00,
        "250" : 0.00,
        "500" : 0.00,
        "750" : 8.00,
        "1000" : 19.50
      },
      "latency_ms" : {
        "2" : 5.00,
        "4" : 3.00,
        "10" : 10.75,
        "20" : 17.25,
        "50" : 31.12,
        "100" : 5.00,
        "250" : 0.12,
        "500" : 0.25,
        "750" : 0.00,
        "1000" : 0.00,
        "2000" : 0.00,
        ">=2000" : 0.00
      },
      "latency_depth" : 1,
      "latency_target" : 0,
      "latency_percentile" : 100.00,
      "latency_window" : 0
    }
  ],
  "disk_util" : [
    {
      "name" : "sda",
      "read_ios" : 632,
      "write_ios" : 169,
      "read_merges" : 0,
      "write_merges" : 5,
      "read_ticks" : 13156,
      "write_ticks" : 1972,
      "in_queue" : 15116,
      "util" : 98.59
    }
  ]
}
