{
  "fio version" : "fio-2.1.11",
  "jobs" : [
    {
      "jobname" : "varwrite",
      "groupid" : 0,
      "error" : 0,
      "read" : {
        "io_bytes" : 41120,
        "bw" : 607,
        "iops" : 75,
        "runtime" : 67681,
        "slat" : {
          "min" : 0,
          "max" : 0,
          "mean" : 0.00,
          "stddev" : 0.00
        },
        "clat" : {
          "min" : 61,
          "max" : 278939,
          "mean" : 11566.81,
          "stddev" : 14431.17,
          "percentile" : {
            "1.000000" : 100,
            "5.000000" : 135,
            "10.000000" : 153,
            "20.000000" : 334,
            "30.000000" : 6112,
            "40.000000" : 6944,
            "50.000000" : 7392,
            "60.000000" : 7712,
            "70.000000" : 8384,
            "80.000000" : 21632,
            "90.000000" : 29568,
            "95.000000" : 36096,
            "99.000000" : 49408,
            "99.500000" : 56576,
            "99.900000" : 195584,
            "99.950000" : 234496,
            "99.990000" : 280576,
            "0.00" : 0,
            "0.00" : 0,
            "0.00" : 0
          }
        },
        "lat" : {
          "min" : 62,
          "max" : 278940,
          "mean" : 11567.34,
          "stddev" : 14431.19
        },
        "bw_min" : 93,
        "bw_max" : 2208,
        "bw_agg" : 100.00,
        "bw_mean" : 608.17,
        "bw_dev" : 447.72
      },
      "write" : {
        "io_bytes" : 163680,
        "bw" : 2418,
        "iops" : 302,
        "runtime" : 67681,
        "slat" : {
          "min" : 0,
          "max" : 0,
          "mean" : 0.00,
          "stddev" : 0.00
        },
        "clat" : {
          "min" : 63,
          "max" : 276976,
          "mean" : 395.38,
          "stddev" : 3943.58,
          "percentile" : {
            "1.000000" : 70,
            "5.000000" : 135,
            "10.000000" : 139,
            "20.000000" : 145,
            "30.000000" : 151,
            "40.000000" : 159,
            "50.000000" : 173,
            "60.000000" : 201,
            "70.000000" : 247,
            "80.000000" : 306,
            "90.000000" : 716,
            "95.000000" : 828,
            "99.000000" : 1512,
            "99.500000" : 1720,
            "99.900000" : 27264,
            "99.950000" : 75264,
            "99.990000" : 211968,
            "0.00" : 0,
            "0.00" : 0,
            "0.00" : 0
          }
        },
        "lat" : {
          "min" : 63,
          "max" : 276977,
          "mean" : 396.22,
          "stddev" : 3943.60
        },
        "bw_min" : 217,
        "bw_max" : 8412,
        "bw_agg" : 100.00,
        "bw_mean" : 2417.95,
        "bw_dev" : 1797.38
      },
      "trim" : {
        "io_bytes" : 0,
        "bw" : 0,
        "iops" : 0,
        "runtime" : 0,
        "slat" : {
          "min" : 0,
          "max" : 0,
          "mean" : 0.00,
          "stddev" : 0.00
        },
        "clat" : {
          "min" : 0,
          "max" : 0,
          "mean" : 0.00,
          "stddev" : 0.00,
          "percentile" : {
            "1.000000" : 0,
            "5.000000" : 0,
            "10.000000" : 0,
            "20.000000" : 0,
            "30.000000" : 0,
            "40.000000" : 0,
            "50.000000" : 0,
            "60.000000" : 0,
            "70.000000" : 0,
            "80.000000" : 0,
            "90.000000" : 0,
            "95.000000" : 0,
            "99.000000" : 0,
            "99.500000" : 0,
            "99.900000" : 0,
            "99.950000" : 0,
            "99.990000" : 0,
            "0.00" : 0,
            "0.00" : 0,
            "0.00" : 0
          }
        },
        "lat" : {
          "min" : 0,
          "max" : 0,
          "mean" : 0.00,
          "stddev" : 0.00
        },
        "bw_min" : 0,
        "bw_max" : 0,
        "bw_agg" : 0.00,
        "bw_mean" : 0.00,
        "bw_dev" : 0.00
      },
      "usr_cpu" : 0.31,
      "sys_cpu" : 1.12,
      "ctx" : 25631,
      "majf" : 0,
      "minf" : 8,
      "iodepth_level" : {
        "1" : 100.00,
        "2" : 0.00,
        "4" : 0.00,
        "8" : 0.00,
        "16" : 0.00,
        "32" : 0.00,
        ">=64" : 0.00
      },
      "latency_us" : {
        "2" : 0.00,
        "4" : 0.00,
        "10" : 0.00,
        "20" : 0.00,
        "50" : 0.00,
        "100" : 1.28,
        "250" : 58.64,
        "500" : 14.29,
        "750" : 3.47,
        "1000" : 5.25
      },
      "latency_ms" : {
        "2" : 1.58,
        "4" : 0.12,
        "10" : 9.48,
        "20" : 1.36,
        "50" : 4.33,
        "100" : 0.12,
        "250" : 0.06,
        "500" : 0.01,
        "750" : 0.00,
        "1000" : 0.00,
        "2000" : 0.00,
        ">=2000" : 0.00
      },
      "latency_depth" : 1,
      "latency_target" : 0,
      "latency_percentile" : 100.00,
      "latency_window" : 0
    }
  ],
  "disk_util" : [
    {
      "name" : "sda",
      "read_ios" : 5140,
      "write_ios" : 20496,
      "read_merges" : 0,
      "write_merges" : 21,
      "read_ticks" : 59076,
      "write_ticks" : 11324,
      "in_queue" : 70340,
      "util" : 97.80
    }
  ]
}
