{
  "fio version" : "fio-2.1.11",
  "jobs" : [
    {
      "jobname" : "varwrite",
      "groupid" : 0,
      "error" : 0,
      "read" : {
        "io_bytes" : 164224,
        "bw" : 1844,
        "iops" : 57,
        "runtime" : 89058,
        "slat" : {
          "min" : 0,
          "max" : 0,
          "mean" : 0.00,
          "stddev" : 0.00
        },
        "clat" : {
          "min" : 154,
          "max" : 419962,
          "mean" : 17087.13,
          "stddev" : 17986.53,
          "percentile" : {
            "1.000000" : 270,
            "5.000000" : 1992,
            "10.000000" : 3856,
            "20.000000" : 7456,
            "30.000000" : 8512,
            "40.000000" : 8512,
            "50.000000" : 8512,
            "60.000000" : 18304,
            "70.000000" : 22656,
            "80.000000" : 27264,
            "90.000000" : 34048,
            "95.000000" : 42752,
            "99.000000" : 56064,
            "99.500000" : 82432,
            "99.900000" : 228352,
            "99.950000" : 261120,
            "99.990000" : 419840,
            "0.00" : 0,
            "0.00" : 0,
            "0.00" : 0
          }
        },
        "lat" : {
          "min" : 154,
          "max" : 419962,
          "mean" : 17087.86,
          "stddev" : 17986.52
        },
        "bw_min" : 589,
        "bw_max" : 2771,
        "bw_agg" : 100.00,
        "bw_mean" : 1848.74,
        "bw_dev" : 442.31
      },
      "write" : {
        "io_bytes" : 40576,
        "bw" : 455,
        "iops" : 14,
        "runtime" : 89058,
        "slat" : {
          "min" : 0,
          "max" : 0,
          "mean" : 0.00,
          "stddev" : 0.00
        },
        "clat" : {
          "min" : 197,
          "max" : 242547,
          "mean" : 1032.10,
          "stddev" : 11086.94,
          "percentile" : {
            "1.000000" : 213,
            "5.000000" : 239,
            "10.000000" : 278,
            "20.000000" : 310,
            "30.000000" : 342,
            "40.000000" : 354,
            "50.000000" : 390,
            "60.000000" : 426,
            "70.000000" : 458,
            "80.000000" : 498,
            "90.000000" : 548,
            "95.000000" : 588,
            "99.000000" : 900,
            "99.500000" : 12608,
            "99.900000" : 226304,
            "99.950000" : 242688,
            "99.990000" : 242688,
            "0.00" : 0,
            "0.00" : 0,
            "0.00" : 0
          }
        },
        "lat" : {
          "min" : 198,
          "max" : 242549,
          "mean" : 1034.99,
          "stddev" : 11086.93
        },
        "bw_min" : 61,
        "bw_max" : 1020,
        "bw_agg" : 100.00,
        "bw_mean" : 456.82,
        "bw_dev" : 204.79
      },
      "trim" : {
        "io_bytes" : 0,
        "bw" : 0,
        "iops" : 0,
        "runtime" : 0,
        "slat" : {
          "min" : 0,
          "max" : 0,
          "mean" : 0.00,
          "stddev" : 0.00
        },
        "clat" : {
          "min" : 0,
          "max" : 0,
          "mean" : 0.00,
          "stddev" : 0.00,
          "percentile" : {
            "1.000000" : 0,
            "5.000000" : 0,
            "10.000000" : 0,
            "20.000000" : 0,
            "30.000000" : 0,
            "40.000000" : 0,
            "50.000000" : 0,
            "60.000000" : 0,
            "70.000000" : 0,
            "80.000000" : 0,
            "90.000000" : 0,
            "95.000000" : 0,
            "99.000000" : 0,
            "99.500000" : 0,
            "99.900000" : 0,
            "99.950000" : 0,
            "99.990000" : 0,
            "0.00" : 0,
            "0.00" : 0,
            "0.00" : 0
          }
        },
        "lat" : {
          "min" : 0,
          "max" : 0,
          "mean" : 0.00,
          "stddev" : 0.00
        },
        "bw_min" : 0,
        "bw_max" : 0,
        "bw_agg" : 0.00,
        "bw_mean" : 0.00,
        "bw_dev" : 0.00
      },
      "usr_cpu" : 0.06,
      "sys_cpu" : 0.36,
      "ctx" : 6415,
      "majf" : 0,
      "minf" : 7,
      "iodepth_level" : {
        "1" : 100.00,
        "2" : 0.00,
        "4" : 0.00,
        "8" : 0.00,
        "16" : 0.00,
        "32" : 0.00,
        ">=64" : 0.00
      },
      "latency_us" : {
        "2" : 0.00,
        "4" : 0.00,
        "10" : 0.00,
        "20" : 0.00,
        "50" : 0.00,
        "100" : 0.00,
        "250" : 1.95,
        "500" : 17.03,
        "750" : 3.88,
        "1000" : 0.08
      },
      "latency_ms" : {
        "2" : 0.75,
        "4" : 4.36,
        "10" : 36.61,
        "20" : 6.52,
        "50" : 27.22,
        "100" : 1.22,
        "250" : 0.33,
        "500" : 0.06,
        "750" : 0.00,
        "1000" : 0.00,
        "2000" : 0.00,
        ">=2000" : 0.00
      },
      "latency_depth" : 1,
      "latency_target" : 0,
      "latency_percentile" : 100.00,
      "latency_window" : 0
    }
  ],
  "disk_util" : [
    {
      "name" : "sda",
      "read_ios" : 5117,
      "write_ios" : 1307,
      "read_merges" : 0,
      "write_merges" : 20,
      "read_ticks" : 87216,
      "write_ticks" : 6200,
      "in_queue" : 93408,
      "util" : 99.43
    }
  ]
}
