{
  "fio version" : "fio-2.1.11",
  "jobs" : [
    {
      "jobname" : "varwrite",
      "groupid" : 0,
      "error" : 0,
      "read" : {
        "io_bytes" : 126272,
        "bw" : 106379,
        "iops" : 1662,
        "runtime" : 1187,
        "slat" : {
          "min" : 0,
          "max" : 0,
          "mean" : 0.00,
          "stddev" : 0.00
        },
        "clat" : {
          "min" : 164,
          "max" : 5259,
          "mean" : 477.94,
          "stddev" : 506.91,
          "percentile" : {
            "1.000000" : 247,
            "5.000000" : 255,
            "10.000000" : 258,
            "20.000000" : 266,
            "30.000000" : 274,
            "40.000000" : 278,
            "50.000000" : 286,
            "60.000000" : 298,
            "70.000000" : 318,
            "80.000000" : 494,
            "90.000000" : 900,
            "95.000000" : 1704,
            "99.000000" : 1880,
            "99.500000" : 3888,
            "99.900000" : 4448,
            "99.950000" : 5280,
            "99.990000" : 5280,
            "0.00" : 0,
            "0.00" : 0,
            "0.00" : 0
          }
        },
        "lat" : {
          "min" : 164,
          "max" : 5259,
          "mean" : 478.34,
          "stddev" : 506.89
        },
        "bw_min" : 100736,
        "bw_max" : 113152,
        "bw_agg" : 100.00,
        "bw_mean" : 106944.00,
        "bw_dev" : 8779.44
      },
      "write" : {
        "io_bytes" : 78528,
        "bw" : 66156,
        "iops" : 1033,
        "runtime" : 1187,
        "slat" : {
          "min" : 0,
          "max" : 0,
          "mean" : 0.00,
          "stddev" : 0.00
        },
        "clat" : {
          "min" : 154,
          "max" : 303,
          "mean" : 183.35,
          "stddev" : 22.34,
          "percentile" : {
            "1.000000" : 157,
            "5.000000" : 157,
            "10.000000" : 157,
            "20.000000" : 169,
            "30.000000" : 173,
            "40.000000" : 175,
            "50.000000" : 179,
            "60.000000" : 181,
            "70.000000" : 191,
            "80.000000" : 195,
            "90.000000" : 215,
            "95.000000" : 229,
            "99.000000" : 258,
            "99.500000" : 266,
            "99.900000" : 286,
            "99.950000" : 302,
            "99.990000" : 302,
            "0.00" : 0,
            "0.00" : 0,
            "0.00" : 0
          }
        },
        "lat" : {
          "min" : 156,
          "max" : 307,
          "mean" : 187.18,
          "stddev" : 23.08
        },
        "bw_min" : 65536,
        "bw_max" : 67712,
        "bw_agg" : 100.00,
        "bw_mean" : 66624.00,
        "bw_dev" : 1538.66
      },
      "trim" : {
        "io_bytes" : 0,
        "bw" : 0,
        "iops" : 0,
        "runtime" : 0,
        "slat" : {
          "min" : 0,
          "max" : 0,
          "mean" : 0.00,
          "stddev" : 0.00
        },
        "clat" : {
          "min" : 0,
          "max" : 0,
          "mean" : 0.00,
          "stddev" : 0.00,
          "percentile" : {
            "1.000000" : 0,
            "5.000000" : 0,
            "10.000000" : 0,
            "20.000000" : 0,
            "30.000000" : 0,
            "40.000000" : 0,
            "50.000000" : 0,
            "60.000000" : 0,
            "70.000000" : 0,
            "80.000000" : 0,
            "90.000000" : 0,
            "95.000000" : 0,
            "99.000000" : 0,
            "99.500000" : 0,
            "99.900000" : 0,
            "99.950000" : 0,
            "99.990000" : 0,
            "0.00" : 0,
            "0.00" : 0,
            "0.00" : 0
          }
        },
        "lat" : {
          "min" : 0,
          "max" : 0,
          "mean" : 0.00,
          "stddev" : 0.00
        },
        "bw_min" : 0,
        "bw_max" : 0,
        "bw_agg" : 0.00,
        "bw_mean" : 0.00,
        "bw_dev" : 0.00
      },
      "usr_cpu" : 2.02,
      "sys_cpu" : 7.42,
      "ctx" : 3204,
      "majf" : 0,
      "minf" : 6,
      "iodepth_level" : {
        "1" : 100.00,
        "2" : 0.00,
        "4" : 0.00,
        "8" : 0.00,
        "16" : 0.00,
        "32" : 0.00,
        ">=64" : 0.00
      },
      "latency_us" : {
        "2" : 0.00,
        "4" : 0.00,
        "10" : 0.00,
        "20" : 0.00,
        "50" : 0.00,
        "100" : 0.00,
        "250" : 38.97,
        "500" : 48.75,
        "750" : 4.59,
        "1000" : 1.59
      },
      "latency_ms" : {
        "2" : 5.53,
        "4" : 0.28,
        "10" : 0.28,
        "20" : 0.00,
        "50" : 0.00,
        "100" : 0.00,
        "250" : 0.00,
        "500" : 0.00,
        "750" : 0.00,
        "1000" : 0.00,
        "2000" : 0.00,
        ">=2000" : 0.00
      },
      "latency_depth" : 1,
      "latency_target" : 0,
      "latency_percentile" : 100.00,
      "latency_window" : 0
    }
  ],
  "disk_util" : [
    {
      "name" : "sdb",
      "read_ios" : 1927,
      "write_ios" : 1198,
      "read_merges" : 0,
      "write_merges" : 0,
      "read_ticks" : 844,
      "write_ticks" : 192,
      "in_queue" : 1036,
      "util" : 82.95
    }
  ]
}
