{
  "fio version" : "fio-2.1.11",
  "jobs" : [
    {
      "jobname" : "varwrite",
      "groupid" : 0,
      "error" : 0,
      "read" : {
        "io_bytes" : 44800,
        "bw" : 62395,
        "iops" : 243,
        "runtime" : 718,
        "slat" : {
          "min" : 0,
          "max" : 0,
          "mean" : 0.00,
          "stddev" : 0.00
        },
        "clat" : {
          "min" : 629,
          "max" : 6355,
          "mean" : 1879.20,
          "stddev" : 1143.86,
          "percentile" : {
            "1.000000" : 628,
            "5.000000" : 684,
            "10.000000" : 692,
            "20.000000" : 756,
            "30.000000" : 1224,
            "40.000000" : 1480,
            "50.000000" : 1656,
            "60.000000" : 1912,
            "70.000000" : 2128,
            "80.000000" : 2384,
            "90.000000" : 3792,
            "95.000000" : 4256,
            "99.000000" : 6048,
            "99.500000" : 6368,
            "99.900000" : 6368,
            "99.950000" : 6368,
            "99.990000" : 6368,
            "0.00" : 0,
            "0.00" : 0,
            "0.00" : 0
          }
        },
        "lat" : {
          "min" : 629,
          "max" : 6355,
          "mean" : 1879.58,
          "stddev" : 1143.88
        },
        "bw_min" : 62339,
        "bw_max" : 62339,
        "bw_agg" : 99.91,
        "bw_mean" : 62339.00,
        "bw_dev" : 0.00
      },
      "write" : {
        "io_bytes" : 160000,
        "bw" : 222841,
        "iops" : 870,
        "runtime" : 718,
        "slat" : {
          "min" : 0,
          "max" : 0,
          "mean" : 0.00,
          "stddev" : 0.00
        },
        "clat" : {
          "min" : 500,
          "max" : 2292,
          "mean" : 605.63,
          "stddev" : 87.97,
          "percentile" : {
            "1.000000" : 540,
            "5.000000" : 556,
            "10.000000" : 564,
            "20.000000" : 588,
            "30.000000" : 588,
            "40.000000" : 588,
            "50.000000" : 596,
            "60.000000" : 604,
            "70.000000" : 604,
            "80.000000" : 612,
            "90.000000" : 660,
            "95.000000" : 668,
            "99.000000" : 692,
            "99.500000" : 732,
            "99.900000" : 2288,
            "99.950000" : 2288,
            "99.990000" : 2288,
            "0.00" : 0,
            "0.00" : 0,
            "0.00" : 0
          }
        },
        "lat" : {
          "min" : 512,
          "max" : 2298,
          "mean" : 615.60,
          "stddev" : 88.08
        },
        "bw_min" : 226874,
        "bw_max" : 226874,
        "bw_agg" : 100.00,
        "bw_mean" : 226874.00,
        "bw_dev" : 0.00
      },
      "trim" : {
        "io_bytes" : 0,
        "bw" : 0,
        "iops" : 0,
        "runtime" : 0,
        "slat" : {
          "min" : 0,
          "max" : 0,
          "mean" : 0.00,
          "stddev" : 0.00
        },
        "clat" : {
          "min" : 0,
          "max" : 0,
          "mean" : 0.00,
          "stddev" : 0.00,
          "percentile" : {
            "1.000000" : 0,
            "5.000000" : 0,
            "10.000000" : 0,
            "20.000000" : 0,
            "30.000000" : 0,
            "40.000000" : 0,
            "50.000000" : 0,
            "60.000000" : 0,
            "70.000000" : 0,
            "80.000000" : 0,
            "90.000000" : 0,
            "95.000000" : 0,
            "99.000000" : 0,
            "99.500000" : 0,
            "99.900000" : 0,
            "99.950000" : 0,
            "99.990000" : 0,
            "0.00" : 0,
            "0.00" : 0,
            "0.00" : 0
          }
        },
        "lat" : {
          "min" : 0,
          "max" : 0,
          "mean" : 0.00,
          "stddev" : 0.00
        },
        "bw_min" : 0,
        "bw_max" : 0,
        "bw_agg" : 0.00,
        "bw_mean" : 0.00,
        "bw_dev" : 0.00
      },
      "usr_cpu" : 3.35,
      "sys_cpu" : 3.91,
      "ctx" : 802,
      "majf" : 0,
      "minf" : 6,
      "iodepth_level" : {
        "1" : 100.00,
        "2" : 0.00,
        "4" : 0.00,
        "8" : 0.00,
        "16" : 0.00,
        "32" : 0.00,
        ">=64" : 0.00
      },
      "latency_us" : {
        "2" : 0.00,
        "4" : 0.00,
        "10" : 0.00,
        "20" : 0.00,
        "50" : 0.00,
        "100" : 0.00,
        "250" : 0.00,
        "500" : 0.00,
        "750" : 82.00,
        "1000" : 1.50
      },
      "latency_ms" : {
        "2" : 8.50,
        "4" : 6.25,
        "10" : 1.75,
        "20" : 0.00,
        "50" : 0.00,
        "100" : 0.00,
        "250" : 0.00,
        "500" : 0.00,
        "750" : 0.00,
        "1000" : 0.00,
        "2000" : 0.00,
        ">=2000" : 0.00
      },
      "latency_depth" : 1,
      "latency_target" : 0,
      "latency_percentile" : 100.00,
      "latency_window" : 0
    }
  ],
  "disk_util" : [
    {
      "name" : "sdb",
      "read_ios" : 157,
      "write_ios" : 567,
      "read_merges" : 0,
      "write_merges" : 0,
      "read_ticks" : 276,
      "write_ticks" : 272,
      "in_queue" : 552,
      "util" : 73.70
    }
  ]
}
