{
  "fio version" : "fio-2.1.11",
  "jobs" : [
    {
      "jobname" : "varwrite",
      "groupid" : 0,
      "error" : 0,
      "read" : {
        "io_bytes" : 46720,
        "bw" : 53762,
        "iops" : 420,
        "runtime" : 869,
        "slat" : {
          "min" : 0,
          "max" : 0,
          "mean" : 0.00,
          "stddev" : 0.00
        },
        "clat" : {
          "min" : 361,
          "max" : 5965,
          "mean" : 1257.62,
          "stddev" : 1028.90,
          "percentile" : {
            "1.000000" : 374,
            "5.000000" : 386,
            "10.000000" : 398,
            "20.000000" : 418,
            "30.000000" : 446,
            "40.000000" : 684,
            "50.000000" : 916,
            "60.000000" : 1256,
            "70.000000" : 1640,
            "80.000000" : 1816,
            "90.000000" : 2288,
            "95.000000" : 3728,
            "99.000000" : 4768,
            "99.500000" : 5344,
            "99.900000" : 5984,
            "99.950000" : 5984,
            "99.990000" : 5984,
            "0.00" : 0,
            "0.00" : 0,
            "0.00" : 0
          }
        },
        "lat" : {
          "min" : 361,
          "max" : 5965,
          "mean" : 1258.04,
          "stddev" : 1028.89
        },
        "bw_min" : 53141,
        "bw_max" : 53141,
        "bw_agg" : 98.84,
        "bw_mean" : 53141.00,
        "bw_dev" : 0.00
      },
      "write" : {
        "io_bytes" : 158080,
        "bw" : 181910,
        "iops" : 1421,
        "runtime" : 869,
        "slat" : {
          "min" : 0,
          "max" : 0,
          "mean" : 0.00,
          "stddev" : 0.00
        },
        "clat" : {
          "min" : 297,
          "max" : 1455,
          "mean" : 318.80,
          "stddev" : 52.96,
          "percentile" : {
            "1.000000" : 298,
            "5.000000" : 302,
            "10.000000" : 302,
            "20.000000" : 302,
            "30.000000" : 302,
            "40.000000" : 306,
            "50.000000" : 306,
            "60.000000" : 314,
            "70.000000" : 322,
            "80.000000" : 326,
            "90.000000" : 334,
            "95.000000" : 354,
            "99.000000" : 430,
            "99.500000" : 572,
            "99.900000" : 1048,
            "99.950000" : 1448,
            "99.990000" : 1448,
            "0.00" : 0,
            "0.00" : 0,
            "0.00" : 0
          }
        },
        "lat" : {
          "min" : 299,
          "max" : 1457,
          "mean" : 323.97,
          "stddev" : 52.97
        },
        "bw_min" : 190850,
        "bw_max" : 190850,
        "bw_agg" : 100.00,
        "bw_mean" : 190850.00,
        "bw_dev" : 0.00
      },
      "trim" : {
        "io_bytes" : 0,
        "bw" : 0,
        "iops" : 0,
        "runtime" : 0,
        "slat" : {
          "min" : 0,
          "max" : 0,
          "mean" : 0.00,
          "stddev" : 0.00
        },
        "clat" : {
          "min" : 0,
          "max" : 0,
          "mean" : 0.00,
          "stddev" : 0.00,
          "percentile" : {
            "1.000000" : 0,
            "5.000000" : 0,
            "10.000000" : 0,
            "20.000000" : 0,
            "30.000000" : 0,
            "40.000000" : 0,
            "50.000000" : 0,
            "60.000000" : 0,
            "70.000000" : 0,
            "80.000000" : 0,
            "90.000000" : 0,
            "95.000000" : 0,
            "99.000000" : 0,
            "99.500000" : 0,
            "99.900000" : 0,
            "99.950000" : 0,
            "99.990000" : 0,
            "0.00" : 0,
            "0.00" : 0,
            "0.00" : 0
          }
        },
        "lat" : {
          "min" : 0,
          "max" : 0,
          "mean" : 0.00,
          "stddev" : 0.00
        },
        "bw_min" : 0,
        "bw_max" : 0,
        "bw_agg" : 0.00,
        "bw_mean" : 0.00,
        "bw_dev" : 0.00
      },
      "usr_cpu" : 3.69,
      "sys_cpu" : 4.61,
      "ctx" : 1603,
      "majf" : 0,
      "minf" : 6,
      "iodepth_level" : {
        "1" : 100.00,
        "2" : 0.00,
        "4" : 0.00,
        "8" : 0.00,
        "16" : 0.00,
        "32" : 0.00,
        ">=64" : 0.00
      },
      "latency_us" : {
        "2" : 0.00,
        "4" : 0.00,
        "10" : 0.00,
        "20" : 0.00,
        "50" : 0.00,
        "100" : 0.00,
        "250" : 0.00,
        "500" : 84.44,
        "750" : 2.38,
        "1000" : 2.12
      },
      "latency_ms" : {
        "2" : 8.12,
        "4" : 2.12,
        "10" : 0.81,
        "20" : 0.00,
        "50" : 0.00,
        "100" : 0.00,
        "250" : 0.00,
        "500" : 0.00,
        "750" : 0.00,
        "1000" : 0.00,
        "2000" : 0.00,
        ">=2000" : 0.00
      },
      "latency_depth" : 1,
      "latency_target" : 0,
      "latency_percentile" : 100.00,
      "latency_window" : 0
    }
  ],
  "disk_util" : [
    {
      "name" : "sdb",
      "read_ios" : 277,
      "write_ios" : 923,
      "read_merges" : 0,
      "write_merges" : 0,
      "read_ticks" : 376,
      "write_ticks" : 216,
      "in_queue" : 592,
      "util" : 79.14
    }
  ]
}
